gco/__init__.py
gco/gco_ext.cp38-win_amd64.pyd
gco/include/GCoptimization.h
gco/include/LinkedBlockList.h
gco/include/block.h
gco/include/energy.h
gco/include/graph.h
gco/include/graph.inl
gco/include/maxflow.inl
gco/lib/gco.lib
gco/lib/cmake/GCO/GCOTargets-release.cmake
gco/lib/cmake/GCO/GCOTargets.cmake
gco-2.0.2.dist-info/METADATA
gco-2.0.2.dist-info/WHEEL
gco-2.0.2.dist-info/top_level.txt
gco-2.0.2.dist-info/RECORD
