Metadata-Version: 2.1
Name: gco
Version: 2.0.2
Summary: Python bindings for the GCO library by Veksler and Delong.
Home-page: https://github.com/agoose77/gco-ext
Author: Angus Hollands
Author-email: goosey15@gmail.com
Project-URL: Research, https://vision.cs.uwaterloo.ca/code
Classifier: Development Status :: 5 - Production/Stable
Classifier: Intended Audience :: Developers
Classifier: Operating System :: OS Independent
Classifier: Programming Language :: Python :: 3
Classifier: Programming Language :: Python :: 3 :: Only
Classifier: Programming Language :: Python :: 3.8
Classifier: Programming Language :: Python :: 3.9
Classifier: Programming Language :: Python :: 3.10
Classifier: Topic :: Scientific/Engineering
Requires-Python: >=3.8
